prestd/__init__.py
prestd/core.py
prestd/models.py
prestd-2026.1.1.dist-info/METADATA
prestd-2026.1.1.dist-info/WHEEL
prestd-2026.1.1.dist-info/top_level.txt
prestd-2026.1.1.dist-info/RECORD
