Metadata-Version: 2.4
Name: prestd
Version: 2026.1.1
Summary: prestd is a Python SDK for pRESTd that provides a fluent, typed, and ergonomic (sync and async) API for interacting with Postgres backed REST endpoints.
Requires-Python: >=3.14
Requires-Dist: httpx>=0.28.1
Requires-Dist: pydantic>=2.12.5
